Pycodz/__init__.py
Pycodz/base.py
Pycodz/exceptions.py
Pycodz/utils.py
Pycodz/ai/__init__.py
Pycodz/ai/main.py
Pycodz-3.6.dist-info/LICENSE
Pycodz-3.6.dist-info/METADATA
Pycodz-3.6.dist-info/WHEEL
Pycodz-3.6.dist-info/top_level.txt
Pycodz-3.6.dist-info/RECORD
