Metadata-Version: 2.2
Name: Pycodz
Version: 3.6
Summary: - Simple Library with Python 3
Home-page: https://github.com/A-X-1/test-lib
Author: AlEx
Author-email: alexcrow221@gmail.com
Classifier: Programming Language :: Python :: 3
Classifier: License :: OSI Approved :: MIT License
Classifier: Operating System :: OS Independent
Requires-Python: >=3.6
License-File: LICENSE
Dynamic: author
Dynamic: author-email
Dynamic: classifier
Dynamic: description
Dynamic: description-content-type
Dynamic: home-page
Dynamic: requires-python
Dynamic: summary
